gz.py
高中数据类型.py
gaozhong_shuju_leixing-0.1.3.dist-info/METADATA
gaozhong_shuju_leixing-0.1.3.dist-info/WHEEL
gaozhong_shuju_leixing-0.1.3.dist-info/top_level.txt
gaozhong_shuju_leixing-0.1.3.dist-info/RECORD
