Metadata-Version: 2.1
Name: gaozhong-shuju-leixing
Version: 0.1.3
Summary: A collection of fundamental data structures implemented in Python
Author: 徐慧琳
Author-email: your.email@example.com
Classifier: Programming Language :: Python :: 3
Classifier: License :: OSI Approved :: MIT License
Classifier: Operating System :: OS Independent
Requires-Python: >=3.6
